wechatpaypy/__init__.py
wechatpaypy/client.py
wechatpaypy/credential.py
wechatpaypy/errors.py
wechatpaypy/main.py
wechatpaypy/validator.py
wechatpay_py-0.0.1.dist-info/LICENSE
wechatpay_py-0.0.1.dist-info/METADATA
wechatpay_py-0.0.1.dist-info/WHEEL
wechatpay_py-0.0.1.dist-info/top_level.txt
wechatpay_py-0.0.1.dist-info/RECORD
