Metadata-Version: 2.1
Name: wechatpay-py
Version: 0.0.1
Summary: A python implementation for wechatpay-apiv3
Home-page: https://github.com/gudong-coding/wechatpay-py
Author: Gudong Coding
Author-email: opensource@gudong.run
License: UNKNOWN
Project-URL: Bug Tracker, https://github.com/gudong-coding/wechatpay-py/issues
Platform: UNKNOWN
Classifier: Programming Language :: Python :: 3
Classifier: License :: OSI Approved :: MIT License
Classifier: Operating System :: OS Independent
Requires-Python: >=3.6
License-File: LICENSE
Requires-Dist: aiohttp
Requires-Dist: orjson
Requires-Dist: pybase64
Requires-Dist: pycryptodome
